{
	"name": "PL_Copy_Customer_Backup",
	"properties": {
		"activities": [
			{
				"name": "CPY_SQL_CSV",
				"type": "Copy",
				"dependsOn": [],
				"policy": {
					"timeout": "0.12:00:00",
					"retry": 0,
					"retryIntervalInSeconds": 30,
					"secureOutput": false,
					"secureInput": false
				},
				"userProperties": [],
				"typeProperties": {
					"source": {
						"type": "SqlServerSource",
						"queryTimeout": "02:00:00",
						"partitionOption": "None"
					},
					"sink": {
						"type": "DelimitedTextSink",
						"storeSettings": {
							"type": "AzureBlobFSWriteSettings"
						},
						"formatSettings": {
							"type": "DelimitedTextWriteSettings",
							"quoteAllText": true,
							"fileExtension": ".txt"
						}
					},
					"enableStaging": false,
					"translator": {
						"type": "TabularTranslator",
						"mappings": [
							{
								"source": {
									"name": "CustomerKey",
									"type": "Int32",
									"physicalType": "int"
								},
								"sink": {
									"name": "CustomerKey",
									"type": "String",
									"physicalType": "String"
								}
							},
							{
								"source": {
									"name": "CustomerID",
									"type": "Int32",
									"physicalType": "int"
								},
								"sink": {
									"name": "CustomerID",
									"type": "String",
									"physicalType": "String"
								}
							},
							{
								"source": {
									"name": "FirstName",
									"type": "String",
									"physicalType": "varchar"
								},
								"sink": {
									"name": "FirstName",
									"type": "String",
									"physicalType": "String"
								}
							},
							{
								"source": {
									"name": "LastName",
									"type": "String",
									"physicalType": "varchar"
								},
								"sink": {
									"name": "LastName",
									"type": "String",
									"physicalType": "String"
								}
							},
							{
								"source": {
									"name": "Email",
									"type": "String",
									"physicalType": "varchar"
								},
								"sink": {
									"name": "Email",
									"type": "String",
									"physicalType": "String"
								}
							},
							{
								"source": {
									"name": "City",
									"type": "String",
									"physicalType": "varchar"
								},
								"sink": {
									"name": "City",
									"type": "String",
									"physicalType": "String"
								}
							},
							{
								"source": {
									"name": "Country",
									"type": "String",
									"physicalType": "varchar"
								},
								"sink": {
									"name": "Country",
									"type": "String",
									"physicalType": "String"
								}
							},
							{
								"source": {
									"name": "StartDate",
									"type": "Date",
									"physicalType": "date"
								},
								"sink": {
									"name": "StartDate",
									"type": "String",
									"physicalType": "String"
								}
							},
							{
								"source": {
									"name": "EndDate",
									"type": "Date",
									"physicalType": "date"
								},
								"sink": {
									"name": "EndDate",
									"type": "String",
									"physicalType": "String"
								}
							},
							{
								"source": {
									"name": "IsCurrent",
									"type": "Boolean",
									"physicalType": "bit"
								},
								"sink": {
									"name": "IsCurrent",
									"type": "String",
									"physicalType": "String"
								}
							}
						],
						"typeConversion": true,
						"typeConversionSettings": {
							"allowDataTruncation": true,
							"treatBooleanAsNumber": false
						}
					}
				},
				"inputs": [
					{
						"referenceName": "DS_SQL_Customer",
						"type": "DatasetReference"
					}
				],
				"outputs": [
					{
						"referenceName": "DS_ADLS_DimCustomer_CSV",
						"type": "DatasetReference"
					}
				]
			}
		],
		"annotations": []
	}
}